core_helpers/__init__.py
core_helpers/cli.py
core_helpers/consts.py
core_helpers/logs.py
core_helpers/py.typed
core_helpers/rich_print.py
core_helpers/updates.py
core_helpers/utils.py
core_helpers/xdg_paths.py
core_helpers-1.3.1.dist-info/LICENSE
core_helpers-1.3.1.dist-info/METADATA
core_helpers-1.3.1.dist-info/WHEEL
core_helpers-1.3.1.dist-info/RECORD
